{"id":213,"pixels":[{"cols":2,"rows":2,"xOffset":0,"yOffset":0,"subpixels":{"1":[],"0":{"1":"#8af046"}}},{"cols":2,"rows":2,"xOffset":2,"yOffset":0,"subpixels":{"1":[],"0":{"1":"#a2832a","0":"#8af046"}}},{"cols":2,"rows":2,"xOffset":4,"yOffset":0,"subpixels":{"1":["#a2832a"],"0":[]}},{"cols":2,"rows":2,"xOffset":6,"yOffset":0,"subpixels":[{"1":"#8af046"},["#a2832a"]]},{"cols":2,"rows":2,"xOffset":0,"yOffset":2,"subpixels":[{"1":"#8af046"},{"1":"#935f31"}]},{"cols":2,"rows":2,"xOffset":2,"yOffset":2,"subpixels":{"1":{"1":"#8af046"},"0":["#8af046"]}},{"cols":2,"rows":2,"xOffset":4,"yOffset":2,"subpixels":{"1":[],"0":["#a2832a"]}},{"cols":2,"rows":2,"xOffset":6,"yOffset":2,"subpixels":{"1":["#fc81d2","#8af046"],"0":[]}},{"cols":2,"rows":2,"xOffset":0,"yOffset":4,"subpixels":{"1":["#dd482d","#8af046"],"0":{"1":"#935f31","0":"#a2832a"}}},{"cols":2,"rows":2,"xOffset":2,"yOffset":4,"subpixels":[[],[]]},{"cols":2,"rows":2,"xOffset":4,"yOffset":4,"subpixels":[[]]},{"cols":2,"rows":2,"xOffset":6,"yOffset":4,"subpixels":[[]]},{"cols":2,"rows":2,"xOffset":0,"yOffset":6,"subpixels":[[],["#935f31","#a2832a"]]},{"cols":2,"rows":2,"xOffset":2,"yOffset":6,"subpixels":{"1":["#a2832a"],"0":["#8af046"]}},{"cols":2,"rows":2,"xOffset":4,"yOffset":6,"subpixels":[["#a2832a","#8af046"],{"1":"#a2832a"}]},{"cols":2,"rows":2,"xOffset":6,"yOffset":6,"subpixels":[[],{"1":"#a2832a","0":"#8af046"}]},{"cols":2,"rows":2,"xOffset":0,"yOffset":8,"subpixels":{"1":[],"0":[]}},{"cols":2,"rows":2,"xOffset":2,"yOffset":8,"subpixels":[{"1":"#54cff7"},[]]},{"cols":2,"rows":2,"xOffset":4,"yOffset":8,"subpixels":{"1":{"1":"#54cff7","0":"#8af046"},"0":["#a2832a"]}},{"cols":2,"rows":2,"xOffset":6,"yOffset":8,"subpixels":[{"1":"#935f31"},[]]},{"cols":2,"rows":2,"xOffset":0,"yOffset":10,"subpixels":{"1":["#54cff7","#8af046"],"0":{"1":"#8af046"}}},{"cols":2,"rows":2,"xOffset":2,"yOffset":10,"subpixels":{"1":["#a2832a","#8af046"],"0":["#8af046"]}},{"cols":2,"rows":2,"xOffset":4,"yOffset":10,"subpixels":[[],["#8af046"]]},{"cols":2,"rows":2,"xOffset":6,"yOffset":10,"subpixels":[[],["#8af046"]]}]}