{"id":173,"pixels":[{"cols":2,"rows":2,"xOffset":0,"yOffset":0,"subpixels":[[],["#6be90b","#44e336"]]},{"cols":2,"rows":2,"xOffset":2,"yOffset":0,"subpixels":[[],{"1":"#44e336"}]},{"cols":2,"rows":2,"xOffset":4,"yOffset":0,"subpixels":[["#44e336"],{"1":"#44e336"}]},{"cols":2,"rows":2,"xOffset":6,"yOffset":0,"subpixels":{"1":{"1":"#f9875f"},"0":["#44e336"]}},{"cols":2,"rows":2,"xOffset":0,"yOffset":2,"subpixels":[["#6be90b","#f9875f"],[]]},{"cols":2,"rows":2,"xOffset":2,"yOffset":2,"subpixels":[{"1":"#44e336"},["#44e336","#44e336"]]},{"cols":2,"rows":2,"xOffset":4,"yOffset":2,"subpixels":[[],["#44e336"]]},{"cols":2,"rows":2,"xOffset":6,"yOffset":2,"subpixels":{"1":[],"0":{"1":"#6be90b"}}},{"cols":2,"rows":2,"xOffset":0,"yOffset":4,"subpixels":{"1":[],"0":["#f9875f","#44e336"]}},{"cols":2,"rows":2,"xOffset":2,"yOffset":4,"subpixels":[[],["#f9875f"]]},{"cols":2,"rows":2,"xOffset":4,"yOffset":4,"subpixels":[["#f9875f"]]},{"cols":2,"rows":2,"xOffset":6,"yOffset":4,"subpixels":{"1":["#44e336"],"0":["#44e336"]}},{"cols":2,"rows":2,"xOffset":0,"yOffset":6,"subpixels":[{"1":"#cc03bb"},{"1":"#f9875f","0":"#44e336"}]},{"cols":2,"rows":2,"xOffset":2,"yOffset":6,"subpixels":[{"1":"#f9875f"},{"1":"#f9875f","0":"#44e336"}]},{"cols":2,"rows":2,"xOffset":4,"yOffset":6,"subpixels":[["#f9875f","#44e336"],[]]},{"cols":2,"rows":2,"xOffset":6,"yOffset":6,"subpixels":[[],{"1":"#f9875f"}]},{"cols":2,"rows":2,"xOffset":0,"yOffset":8,"subpixels":[["#44e336"],["#f9875f"]]},{"cols":2,"rows":2,"xOffset":2,"yOffset":8,"subpixels":{"1":[],"0":{"1":"#44e336"}}},{"cols":2,"rows":2,"xOffset":4,"yOffset":8,"subpixels":{"1":[],"0":[]}},{"cols":2,"rows":2,"xOffset":6,"yOffset":8,"subpixels":{"1":{"1":"#12cabe"},"0":["#44e336"]}},{"cols":2,"rows":2,"xOffset":0,"yOffset":10,"subpixels":[{"1":"#f9875f"},["#44e336"]]},{"cols":2,"rows":2,"xOffset":2,"yOffset":10,"subpixels":{"1":[],"0":["#44e336"]}},{"cols":2,"rows":2,"xOffset":4,"yOffset":10,"subpixels":[["#44e336"],[]]},{"cols":2,"rows":2,"xOffset":6,"yOffset":10,"subpixels":{"1":{"1":"#f9875f"},"0":{"1":"#44e336"}}}]}